jpeg/__init__.py
jpegtran-0.0.3.dist-info/LICENSE
jpegtran-0.0.3.dist-info/METADATA
jpegtran-0.0.3.dist-info/WHEEL
jpegtran-0.0.3.dist-info/top_level.txt
jpegtran-0.0.3.dist-info/RECORD
